winstats.py
winstats-0.80.dist-info/METADATA
winstats-0.80.dist-info/WHEEL
winstats-0.80.dist-info/top_level.txt
winstats-0.80.dist-info/RECORD
