Metadata-Version: 2.1
Name: winstats
Version: 0.80
Summary: A simple Windows status retrieval module with no additional dependencies.
Home-page: https://github.com/mixmastamyk/winstats
Author: Mike Miller
Author-email: mixmastamyk@bitbucket.org
License: UNKNOWN
Download-URL: https://github.com/mixmastamyk/winstats/get/default.tar.gz
Platform: UNKNOWN
Classifier: Development Status :: 4 - Beta
Classifier: Environment :: Win32 (MS Windows)
Classifier: Intended Audience :: Developers
Classifier: Intended Audience :: System Administrators
Classifier: License :: OSI Approved :: GNU Lesser General Public License v3 or later (LGPLv3+)
Classifier: Operating System :: Microsoft :: Windows :: Windows 7
Classifier: Operating System :: Microsoft :: Windows :: Windows XP
Classifier: Programming Language :: Python
Classifier: Programming Language :: Python :: 2.7
Classifier: Programming Language :: Python :: 3.5
Classifier: Topic :: System :: Hardware
Classifier: Topic :: System :: Monitoring
Classifier: Topic :: System :: Systems Administration
Classifier: Topic :: Software Development :: Libraries
